karya/clients/__init__.py
karya/clients/config.py
karya/clients/requests.py
karya/clients/responses.py
karya/entities/__init__.py
karya/entities/abstracts.py
karya/entities/actions.py
karya/entities/enums.py
karya/entities/plan_types.py
karya_client-1.1.3.dist-info/LICENSE
karya_client-1.1.3.dist-info/METADATA
karya_client-1.1.3.dist-info/WHEEL
karya_client-1.1.3.dist-info/RECORD
