Metadata-Version: 2.1
Name: karya-client
Version: 1.1.3
Summary: Python client to interract with Karya; the open sourced distributed job scheduler
Home-page: https://saumya-bhatt.github.io/karya-python-client/
Author: Saumya Bhatt
Author-email: 108668549+SaumyaBhatt106@users.noreply.github.com
Requires-Python: >=3.10,<4.0
Classifier: Programming Language :: Python :: 3
Classifier: Programming Language :: Python :: 3.10
Classifier: Programming Language :: Python :: 3.11
Classifier: Programming Language :: Python :: 3.12
Classifier: Programming Language :: Python :: 3.13
Requires-Dist: httpx (>=0.28.1,<0.29.0)
Requires-Dist: pydantic (>=2.10.3,<3.0.0)
Requires-Dist: ruff (>=0.8.3,<0.9.0)
Requires-Dist: sphinx (>=8.1.3,<9.0.0)
Requires-Dist: sphinx-rtd-theme (>=3.0.2,<4.0.0)
Project-URL: Documentation, https://saumya-bhatt.github.io/karya-python-client/
Project-URL: Repository, https://github.com/Saumya-Bhatt/karya-python-client
